{
  "slug": "nelson-mandela-long-walk",
  "title": "Nelson Mandela: Long Walk Out of the Cell",
  "person": "Nelson Mandela",
  "years": "1918–2013",
  "dek": "The prisoner who helped turn 27 stolen years into a democratic transfer of power.",
  "mortality_event": "Faced the death penalty at Rivonia, then spent 27 years imprisoned before leading South Africa through democratic transition.",
  "published_at": "2026-06-12",
  "pages": [
    "pages/01-nelson-mandela-long-walk.jpg",
    "pages/02-nelson-mandela-long-walk.jpg",
    "pages/03-nelson-mandela-long-walk.jpg",
    "pages/04-nelson-mandela-long-walk.jpg",
    "pages/05-nelson-mandela-long-walk.jpg",
    "pages/06-nelson-mandela-long-walk.jpg",
    "pages/07-nelson-mandela-long-walk.jpg"
  ],
  "page_dimensions": {
    "pages/01-nelson-mandela-long-walk.jpg": [
      1440,
      1920
    ],
    "pages/02-nelson-mandela-long-walk.jpg": [
      1440,
      1920
    ],
    "pages/03-nelson-mandela-long-walk.jpg": [
      1440,
      1920
    ],
    "pages/04-nelson-mandela-long-walk.jpg": [
      1440,
      1920
    ],
    "pages/05-nelson-mandela-long-walk.jpg": [
      1440,
      1920
    ],
    "pages/06-nelson-mandela-long-walk.jpg": [
      1440,
      1920
    ],
    "pages/07-nelson-mandela-long-walk.jpg": [
      1440,
      1920
    ]
  },
  "sources": [
    {
      "name": "Nelson Mandela Foundation",
      "url": "https://www.nelsonmandela.org/content/page/biography"
    },
    {
      "name": "Nobel Prize",
      "url": "https://www.nobelprize.org/prizes/peace/1993/mandela/biographical/"
    },
    {
      "name": "Wikipedia",
      "url": "https://en.wikipedia.org/wiki/Nelson_Mandela"
    }
  ],
  "pdf": "nelson-mandela-long-walk.pdf",
  "contact_sheet": "contact-sheet.jpg"
}
